Metadata-Version: 2.1
Name: mojiconverter
Version: 0.0.1
Summary: moji converter
Home-page: https://github.com/venkatzgithub/moji-converter
Author: Venkat Prasad
Author-email: imvenkatprasad@gmail.com
License: MIT
Keywords: python,moji,hiragana,katakana,converter,japanese
Platform: UNKNOWN
Classifier: License :: OSI Approved :: MIT License
Classifier: Programming Language :: Python :: 3
Classifier: Programming Language :: Python :: 3.7
